azcam_scripts/__init__.py
azcam_scripts/centroids.py
azcam_scripts/check_bits.py
azcam_scripts/display_files.py
azcam_scripts/exposure_timer.py
azcam_scripts/get_pressures.py
azcam_scripts/get_temperatures.py
azcam_scripts/plot_header_times.py
azcam_scripts/plot_images.py
azcam_scripts/plot_keywords.py
azcam_scripts/plot_log_temps.py
azcam_scripts/readnoise_correction.py
azcam_scripts/scan_wavelengths.py
azcam_scripts/show_histogram.py
azcam_scripts/show_sequence_keywords.py
azcam_scripts/show_sequence_stats.py
azcam_scripts/test_arc_controller.py
azcam_scripts/test_communications.py
azcam_scripts/test_controller.py
azcam_scripts/test_exposures.py
azcam_scripts/test_filters.py
azcam_scripts/test_gain_stability.py
azcam_scripts/test_instrument.py
azcam_scripts/test_mag_controller.py
azcam_scripts/test_reset.py
azcam_scripts/test_shutter.py
azcam_scripts/test_temperatures.py
azcam_scripts/test_wavelengths.py
azcam_scripts/test_web.py
azcam_scripts/threshold_image.py
azcam_scripts-22.3.3.dist-info/LICENSE
azcam_scripts-22.3.3.dist-info/WHEEL
azcam_scripts-22.3.3.dist-info/METADATA
azcam_scripts-22.3.3.dist-info/RECORD
