Metadata-Version: 2.1
Name: azcam-scripts
Version: 22.3.3
Summary: Azcam extension which adds general purpose scripts
Keywords: ccd,imaging,astronomy,sensors
Author: Michael Lesser
Author-email: mlesser@arizona.edu
Requires-Dist: azcam
Requires-Dist: scipy
Requires-Dist: astropy
Requires-Dist: matplotlib
Requires-Dist: numpy
Requires-Dist: requests
Project-URL: Documentation, https://mplesser.github.io/azcam/
Project-URL: Repository, https://github.com/mplesser/azcam-scripts/
